Workbook

Sheet Inputs
A1: Bali Yatra 21-26 Jun 2027: inputs (yellow = edit; paste new quotes in column D, it overrides column B)
A3: Item | B3: Default | C3: Unit | D3: New quote (paste here) | E3: Effective value | F3: Source / status
A4: IDR per Rs 1 (today) | B4: 190.6446 | C4: IDR | E4: =IF(D4="",B4,D4) -> 190.6446 | F4: XE mid-market, 23 Oct 2026
A5: IDR per Rs 1 (previous basis) | B5: 185 | C5: IDR | E5: =IF(D5="",B5,D5) -> 185 | F5: Approx. Pluang, 22 Jul 2026 (184.8 to 185.8)
A6: Paying yatris (planning size) | B6: 35 | C6: persons | E6: =IF(D6="",B6,D6) -> 35 | F6: Decision: 30 or more
A7: Tour managers (our team) | B7: 1 | C7: persons | E7: =IF(D7="",B7,D7) -> 1 | F7: Assumption, confirm
A8: Accompanying devotees (cost borne by us) | B8: 2 | C8: persons | E8: =IF(D8="",B8,D8) -> 2 | F8: Assumption, confirm (cook, kirtan lead, doctor etc.)
A9: Target margin on selling price | B9: 0.1 | C9: % | E9: =IF(D9="",B9,D9) -> 0.1 | F9: ASSUMPTION: not given yet, replace
A10: GST on package | B10: 0.05 | C10: % | E10: =IF(D10="",B10,D10) -> 0.05 | F10: 5% without ITC per secondary sources; CA to confirm
A11: TCS on overseas tour package | B11: 0.02 | C11: % | E11: =IF(D11="",B11,D11) -> 0.02 | F11: 2% flat from 1 Apr 2026 (news/blogs); CA to confirm
A12: Contingency on cost | B12: 0.03 | C12: % | E12: =IF(D12="",B12,D12) -> 0.03 | F12: Planning allowance, edit
A13: Bank / payment charges on selling price | B13: 0.015 | C13: % | E13: =IF(D13="",B13,D13) -> 0.015 | F13: ASSUMPTION: confirm with bank
A14: Seats per coach | B14: 35 | C14: seats | E14: =IF(D14="",B14,D14) -> 35 | F14: Operator quote: max 30-35 seater
A15: Extra coach, cost per day | B15: 1900000 | C15: IDR | E15: =IF(D15="",B15,D15) -> 1900000 | F15: NOT VERIFIED: 27-seat 12h rate used as floor (mybalitrips.com)
... A25: Hyderabad local transfers per yatri | B25: 0 | C25: Rs | E25: =IF(D25="",B25,D25) -> 0 | F25: TBC: no quote yet
A26: Proposed selling price per yatri, before GST (optional) | C26: Rs | E26: =IF(D26="",B26,D26) -> 0 | F26: Enter to see the margin it gives

Sheet Itinerary
A1: Day-by-day itinerary (tentative: flights and ashram timings not confirmed; km are approximate, check each link before fixing)
A3: Day | B3: Date | C3: Start | D3: End | E3: Clock shift (h) | F3: Duration (h) | G3: Duration | H3: Activity | I3: Place | J3: Google Maps | K3: Transport | L3: Approx km | M3: What we do | N3: Meal / who provides
A4: 1 | B4: 46559 | C4: 46559.729 | D4: 46559.781 | E4: 0 | F4: =ROUND(((D4-C4)*24)-E4,2) -> 1.25 | G4: =INT(F4)&"h "&TEXT(ROUND(MOD(F4,1)*60,0),"00")&"m" -> 1h 15m | H4: Satvik dinner and pre-departure briefing | I4: Hare Krishna Golden Temple, Hyderabad | J4: Open map | K4: On foot | L4: 0 | M4: Prasadam, briefing on documents, dress, health, group rules. Garland the Deities, offer prayers for a safe yatra. | N4: Dinner: HKGT prasadam (confirm)
A5: 1 | B5: 46559 | C5: 46559.781 | D5: 46559.833 | E5: 0 | F5: =ROUND(((D5-C5)*24)-E5,2) -> 1.25 | G5: =INT(F5)&"h "&TEXT(ROUND(MOD(F5,1)*60,0),"00")&"m" -> 1h 15m | H5: Coach to airport | I5: Rajiv Gandhi International Airport, Hyderabad | J5: Open map | K5: Coach | L5: 30 | M5: Allow 1h15m for evening traffic. | N5: -
A6: 1 | B6: 46559 | C6: 46559.833 | D6: 46559.997 | E6: 0 | F6: =ROUND(((D6-C6)*24)-E6,2) -> 3.92 | G6: =INT(F6)&"h "&TEXT(ROUND(MOD(F6,1)*60,0),"00")&"m" -> 3h 55m | H6: Group check-in, emigration, boarding | I6: Rajiv Gandhi International Airport, Hyderabad | J6: Open map | K6: Walk | L6: 0 | M6: Report 3h 55m before departure; seniors get wheelchair help on request. | N6: Own snacks (Satvik kit)
A7: 1 | B7: 46559 | C7: 46559.997 | D7: 46560.292 | E7: 2.5 | F7: =ROUND(((D7-C7)*24)-E7,2) -> 4.58 | G7: =INT(F7)&"h "&TEXT(ROUND(MOD(F7,1)*60,0),"00")&"m" -> 4h 35m | H7: Flight HYD to Kuala Lumpur (AirAsia AK068, TENTATIVE) | I7: Kuala Lumpur International Airport | J7: Open map | K7: Flight | L7: 0 | M7: Schedule from Oct 2026 snapshot; June 2027 not open. Operates Mon/Tue/Wed/Sat in that pattern. | N7: On board: own prasadam snacks
A8: 2 | B8: 46560 | C8: 46560.292 | D8: 46560.375 | E8: 0 | F8: =ROUND(((D8-C8)*24)-E8,2) -> 2 | G8: =INT(F8)&"h "&TEXT(ROUND(MOD(F8,1)*60,0),"00")&"m" -> 2h 00m | H8: Transit at Kuala Lumpur | I8: Kuala Lumpur International Airport | J8: Open map | K8: Walk | L8: 0 | M8: Immigration and transit; Satvik breakfast kit from Hyderabad. | N8: Breakfast: carried Satvik kit
A9: 2 | B9: 46560 | C9: 46560.375 | D9: 46560.51 | E9: 0 | F9: =ROUND(((D9-C9)*24)-E9,2) -> 3.25 | G9: =INT(F9)&"h "&TEXT(ROUND(MOD(F9,1)*60,0),"00")&"m" -> 3h 15m | H9: Flight KUL to Bali (AirAsia AK364, TENTATIVE) | I9: Ngurah Rai International Airport, Bali | J9: Open map | K9: Flight | L9: 0 | M9: KUL and Bali share the same time zone (UTC+8). | N9: On board: own snacks
A10: 2 | B10: 46560 | C10: 46560.51 | D10: 46560.583 | E10: 0 | F10: =ROUND(((D10-C10)*24)-E10,2) -> 1.75 | G10: =INT(F10)&"h "&TEXT(ROUND(MOD(F10,1)*60,0),"00")&"m" -> 1h 45m | H10: Arrival: immigration (e-VOA), bags, meet guide | I10: Ngurah Rai International Airport, Bali | J10: Open map | K10: Walk | L10: 0 | M10: Pre-paid e-VOA and arrival card QR codes ready. Levy vouchers. Allow 1h 45m for 35 persons. | N10: -
A11: 2 | B11: 46560 | C11: 46560.583 | D11: 46560.597 | E11: 0 | F11: =ROUND(((D11-C11)*24)-E11,2) -> 0.33 | G11: =INT(F11)&"h "&TEXT(ROUND(MOD(F11,1)*60,0),"00")&"m" -> 0h 20m | H11: Coach to lunch | I11: Vrindavan Pure Veg Restaurant, Kuta | J11: Open map | K11: Coach | L11: 5 | M11: Short hop from the airport. | N11: -
A12: 2 | B12: 46560 | C12: 46560.597 | D12: 46560.646 | E12: 0 | F12: =ROUND(((D12-C12)*24)-E12,2) -> 1.17 | G12: =INT(F12)&"h "&TEXT(ROUND(MOD(F12,1)*60,0),"00")&"m" -> 1h 10m | H12: Lunch | I12: Vrindavan Pure Veg Restaurant, Kuta | J12: Open map | K12: On foot | L12: 0 | M12: Confirm group size, no onion-garlic cooking and booking in writing. Fallback: pre-ordered boxed lunch. | N12: Lunch: Indian pure-veg restaurant (to book)
A13: 2 | B13: 46560 | C13: 46560.646 | D13: 46560.698 | E13: 0 | F13: =ROUND(((D13-C13)*24)-E13,2) -> 1.25 | G13: =INT(F13)&"h "&TEXT(ROUND(MOD(F13,1)*60,0),"00")&"m" -> 1h 15m | H13: Coach to ISKCON Bali | I13: Sri Sri Radha Madhava Mandir, Bitera, Gianyar | J13: Open map | K13: Coach | L13: 35 | M13: Address from a 2011 article: confirm location and timings with the temple. | N13: -
A14: 2 | B14: 46560 | C14: 46560.698 | D14: 46560.792 | E14: 0 | F14: =ROUND(((D14-C14)*24)-E14,2) -> 2.25 | G14: =INT(F14)&"h "&TEXT(ROUND(MOD(F14,1)*60,0),"00")&"m" -> 2h 15m | H14: Darshan, kirtan and prasadam at ISKCON Bali (TIMINGS TBC) | I14: Sri Sri Radha Madhava Mandir, Bitera, Gianyar | J14: Open map | K14: On foot | L14: 0 | M14: Temple darshan and sandhya arati if timed; group prasadam dinner only if the temple agrees (not verified). | N14: Dinner: ISKCON Bali prasadam (to request)
A15: 2 | B15: 46560 | C15: 46560.792 | D15: 46560.823 | E15: 0 | F15: =ROUND(((D15-C15)*24)-E15,2) -> 0.75 | G15: =INT(F15)&"h "&TEXT(ROUND(MOD(F15,1)*60,0),"00")&"m" -> 0h 45m | H15: Coach to Ubud hotel | I15: Ubud hotel (hotel TBC) | J15: Open map | K15: Coach | L15: 15 | M15: Distance is approximate. | N15: -
... A57: 6 | B57: 46564 | C57: 46564.892 | D57: 46564.972 | E57: -2.5 | F57: =ROUND(((D57-C57)*24)-E57,2) -> 4.42 | G57: =INT(F57)&"h "&TEXT(ROUND(MOD(F57,1)*60,0),"00")&"m" -> 4h 25m | H57: Flight KUL to Hyderabad (ASSUMED: MH198 pattern) | I57: Rajiv Gandhi International Airport, Hyderabad | J57: Open map | K57: Flight | L57: 0 | M57: Arrival time is India time (IST). NOT VERIFIED for 2027. | N57: On board: own snacks

Sheet Day summary
A1: Day summary (formulas read the Itinerary sheet)
A3: Day | B3: Date | C3: Route | D3: Overnight | E3: Approx km | F3: Coach hours | G3: Flight hours (clock-adjusted) | H3: Driver check (8h baseline) | I3: Sunrise | J3: Sunset
A4: 1 | B4: 46559 | C4: Hyderabad to airport, overnight flight via Kuala Lumpur | D4: In flight | E4: =SUMIFS(Itinerary!$L$4:$L$57,Itinerary!$A$4:$A$57,A4) -> 30 | F4: =SUMIFS(Itinerary!$F$4:$F$57,Itinerary!$A$4:$A$57,A4,Itinerary!$K$4:$K$57,"Coach") -> 1.25 | G4: =SUMIFS(Itinerary!$F$4:$F$57,Itinerary!$A$4:$A$57,A4,Itinerary!$K$4:$K$57,"Flight") -> 4.58 | H4: =IF(F4>8,"CHECK: over 8h","OK") -> OK | I4: n/a (Hyderabad) | J4: n/a
A5: 2 | B5: 46560 | C5: Kuala Lumpur, Bali airport, Kuta lunch, ISKCON Bitera, Ubud | D5: Ubud | E5: =SUMIFS(Itinerary!$L$4:$L$57,Itinerary!$A$4:$A$57,A5) -> 55 | F5: =SUMIFS(Itinerary!$F$4:$F$57,Itinerary!$A$4:$A$57,A5,Itinerary!$K$4:$K$57,"Coach") -> 2.33 | G5: =SUMIFS(Itinerary!$F$4:$F$57,Itinerary!$A$4:$A$57,A5,Itinerary!$K$4:$K$57,"Flight") -> 3.25 | H5: =IF(F5>8,"CHECK: over 8h","OK") -> OK | I5: 06:32 | J5: 18:09
A6: 3 | B6: 46561 | C6: Tirta Empul, Ubud, Monkey Forest, Saraswati | D6: Ubud | E6: =SUMIFS(Itinerary!$L$4:$L$57,Itinerary!$A$4:$A$57,A6) -> 38 | F6: =SUMIFS(Itinerary!$F$4:$F$57,Itinerary!$A$4:$A$57,A6,Itinerary!$K$4:$K$57,"Coach") -> 1.5 | G6: =SUMIFS(Itinerary!$F$4:$F$57,Itinerary!$A$4:$A$57,A6,Itinerary!$K$4:$K$57,"Flight") -> 0 | H6: =IF(F6>8,"CHECK: over 8h","OK") -> OK | I6: 06:32 | J6: 18:09
A7: 4 | B7: 46562 | C7: Ubud to Bedugul to Kuta, Tanah Lot | D7: Kuta | E7: =SUMIFS(Itinerary!$L$4:$L$57,Itinerary!$A$4:$A$57,A7) -> 150 | F7: =SUMIFS(Itinerary!$F$4:$F$57,Itinerary!$A$4:$A$57,A7,Itinerary!$K$4:$K$57,"Coach") -> 5.75 | G7: =SUMIFS(Itinerary!$F$4:$F$57,Itinerary!$A$4:$A$57,A7,Itinerary!$K$4:$K$57,"Flight") -> 0 | H7: =IF(F7>8,"CHECK: over 8h","OK") -> OK | I7: 06:32 | J7: 18:10
A8: 5 | B8: 46563 | C8: GWK, Kuta, Uluwatu | D8: Kuta | E8: =SUMIFS(Itinerary!$L$4:$L$57,Itinerary!$A$4:$A$57,A8) -> 99 | F8: =SUMIFS(Itinerary!$F$4:$F$57,Itinerary!$A$4:$A$57,A8,Itinerary!$K$4:$K$57,"Coach") -> 3.58 | G8: =SUMIFS(Itinerary!$F$4:$F$57,Itinerary!$A$4:$A$57,A8,Itinerary!$K$4:$K$57,"Flight") -> 0 | H8: =IF(F8>8,"CHECK: over 8h","OK") -> OK | I8: 06:33 | J8: 18:10
A9: 6 | B9: 46564 | C9: Krishna Oleh-Oleh, airport, flights home | D9: In flight / Hyderabad (late night) | E9: =SUMIFS(Itinerary!$L$4:$L$57,Itinerary!$A$4:$A$57,A9) -> 17 | F9: =SUMIFS(Itinerary!$F$4:$F$57,Itinerary!$A$4:$A$57,A9,Itinerary!$K$4:$K$57,"Coach") -> 1.5 | G9: =SUMIFS(Itinerary!$F$4:$F$57,Itinerary!$A$4:$A$57,A9,Itinerary!$K$4:$K$57,"Flight") -> 7.59 | H9: =IF(F9>8,"CHECK: over 8h","OK") -> OK | I9: 06:33 | J9: 18:10
A10: Total | E10: =SUM(E4:E9) -> 389 | F10: =SUM(F4:F9) -> 15.91 | G10: =SUM(G4:G9) -> 15.42
A12: Sunrise and sunset: Denpasar, sunrise-sunset.org, checked 23 Oct 2026. Driver-hour baseline: Indonesian Law 22/2009 Art. 90 (8h/day, 30 min rest after 4h); local confirmation pending.
A13: Coach hours count driving legs only; short hops to and from hotel rests (about 20 min) are not counted.

Sheet Meal plan
A1: Meal plan (Satvik only: no onion, garlic, eggs, meat, fish). No Ekadasi on 21-26 Jun 2027 (Nirjala 14/15 Jun; Yogini 30 Jun).
A3: Day | B3: Date | C3: Breakfast | D3: Lunch | E3: Dinner | F3: Notes
A4: 1 | B4: 46559 | C4: Home | D4: Home | E4: HKGT prasadam before departure (confirm); Satvik snack kit on the flight | F4: Pack Satvik kit for the long journey
A5: 2 | B5: 46560 | C5: Carried Satvik kit at KUL | D5: Vrindavan Pure Veg, Kuta (to book) | E5: ISKCON Bali prasadam (to request); fallback hotel | F5: Written Satvik confirmation needed from every provider
A6: 3 | B6: 46561 | C6: Ubud hotel | D6: Madhubann Pure Veg Indian, Ubud (to book) | E6: Ubud hotel | F6: Hotel kitchen must cook without onion/garlic
A7: 4 | B7: 46562 | C7: Ubud hotel | D7: Boxed Satvik lunch at Bedugul (to book) | E7: Kuta hotel or Shiv Sagar, Seminyak (to book) | F7: No verified restaurant near Bedugul
A8: 5 | B8: 46563 | C8: Kuta hotel | D8: Vinayak, Lippo Mall Kuta (to book) | E8: Kuta hotel | F8: Kecak evening is optional; dinner may be late
A9: 6 | B9: 46564 | C9: Kuta hotel | D9: Vrindavan Pure Veg, Kuta (to book) | E9: Carried Satvik kit at KUL | F9: Hyderabad arrival about 23:20

Sheet Tickets
A1: Entry tickets, adult rate (not official except Monkey Forest; no senior or group concession found). IDR converted at Inputs rate.
A3: Site | B3: Status | C3: Adult IDR | D3: Adult Rs | E3: Qty (yatris) | F3: Total IDR | G3: Total Rs | H3: Source / note
A4: Sacred Monkey Forest, Ubud | B4: Planned | C4: 130000 | D4: =ROUND(C4/Inputs!$E$4,0) -> 682 | E4: =Inputs!$E$6 -> 35 | F4: =C4*E4 -> 4550000 | G4: =ROUND(F4/Inputs!$E$4,0) -> 23866 | H4: Official site
A5: Tirta Empul | B5: Planned | C5: 75000 | D5: =ROUND(C5/Inputs!$E$4,0) -> 393 | E5: =Inputs!$E$6 -> 35 | F5: =C5*E5 -> 2625000 | G5: =ROUND(F5/Inputs!$E$4,0) -> 13769 | H5: Guide, baliholidaysecrets.com; others say 50,000
A6: Pura Ulun Danu Beratan | B6: Planned | C6: 100000 | D6: =ROUND(C6/Inputs!$E$4,0) -> 525 | E6: =Inputs!$E$6 -> 35 | F6: =C6*E6 -> 3500000 | G6: =ROUND(F6/Inputs!$E$4,0) -> 18359 | H6: Same guide; others 50,000 to 75,000
A7: Taman Saraswati, Ubud | B7: Planned | C7: 60000 | D7: =ROUND(C7/Inputs!$E$4,0) -> 315 | E7: =Inputs!$E$6 -> 35 | F7: =C7*E7 -> 2100000 | G7: =ROUND(F7/Inputs!$E$4,0) -> 11015 | H7: Guide conflict (free to 60,000): upper used
A8: Tanah Lot | B8: Planned | C8: 75000 | D8: =ROUND(C8/Inputs!$E$4,0) -> 393 | E8: =Inputs!$E$6 -> 35 | F8: =C8*E8 -> 2625000 | G8: =ROUND(F8/Inputs!$E$4,0) -> 13769 | H8: Same guide
A9: GWK Cultural Park | B9: Planned | C9: 150000 | D9: =ROUND(C9/Inputs!$E$4,0) -> 787 | E9: =Inputs!$E$6 -> 35 | F9: =C9*E9 -> 5250000 | G9: =ROUND(F9/Inputs!$E$4,0) -> 27538 | H9: Same guide; official site shows price only after date selection
A10: Uluwatu Temple | B10: Planned | C10: 60000 | D10: =ROUND(C10/Inputs!$E$4,0) -> 315 | E10: =Inputs!$E$6 -> 35 | F10: =C10*E10 -> 2100000 | G10: =ROUND(F10/Inputs!$E$4,0) -> 11015 | H10: Same guide; another says 50,000
A11: Kecak fire dance, Uluwatu | B11: Optional | C11: 150000 | D11: =ROUND(C11/Inputs!$E$4,0) -> 787 | E11: =Inputs!$E$6 -> 35 | F11: =C11*E11 -> 5250000 | G11: =ROUND(F11/Inputs!$E$4,0) -> 27538 | H11: Same guide; 100,000 to 200,000 elsewhere
A12: Goa Gajah | B12: Optional | C12: 50000 | D12: =ROUND(C12/Inputs!$E$4,0) -> 262 | E12: =Inputs!$E$6 -> 35 | F12: =C12*E12 -> 1750000 | G12: =ROUND(F12/Inputs!$E$4,0) -> 9179 | H12: Not in route; kept as option
A13: Tegallalang rice terrace | B13: Optional | C13: 50000 | D13: =ROUND(C13/Inputs!$E$4,0) -> 262 | E13: =Inputs!$E$6 -> 35 | F13: =C13*E13 -> 1750000 | G13: =ROUND(F13/Inputs!$E$4,0) -> 9179 | H13: Not recommended for seniors
A14: Ubud Palace | B14: Optional | C14: 0 | D14: =ROUND(C14/Inputs!$E$4,0) -> 0 | E14: =Inputs!$E$6 -> 35 | F14: =C14*E14 -> 0 | G14: =ROUND(F14/Inputs!$E$4,0) -> 0 | H14: Free per guide
A15: ISKCON Bali ashram | B15: Planned | C15: 0 | D15: =ROUND(C15/Inputs!$E$4,0) -> 0 | E15: =Inputs!$E$6 -> 35 | F15: =C15*E15 -> 0 | G15: =ROUND(F15/Inputs!$E$4,0) -> 0 | H15: Voluntary donation
A17: Planned total per adult | C17: =SUMIFS(C4:C15,B4:B15,"Planned") -> 650000 | D17: =ROUND(C17/Inputs!$E$4,0) -> 3409 | F17: =SUMIFS(F4:F15,B4:B15,"Planned") -> 22750000 | G17: =ROUND(F17/Inputs!$E$4,0) -> 119332
A18: Optional total per adult (if all taken) | C18: =SUMIFS(C4:C15,B4:B15,"Optional") -> 250000 | D18: =ROUND(C18/Inputs!$E$4,0) -> 1311
A20: Tickets are assumed to be inside the operator land package (the quote says both yes and no). If not, add the planned total to the budget as a cost.

Sheet Budget
A1: Budget per yatri at the planning size (Inputs!B6). Previous basis = old FX and old visa fee; Current = today's rate and latest quotes.
A3: Line | B3: Previous basis Rs | C3: Current Rs | D3: Change Rs | E3: Change % | F3: Status
A4: Return flights HYD-KUL-DPS | B4: =Inputs!$E$17 -> 48000 | C4: =Inputs!$E$17 -> 48000 | D4: =C4-B4 -> 0 | E4: =IF(B4=0,0,D4/B4) -> 0 | F4: PLACEHOLDER: old ex-Bangalore airfare
A5: Land package, 4 nights twin (hotels, meals, coach, guide, tips, tickets) | B5: =Inputs!$E$18 -> 35000 | C5: =Inputs!$E$18 -> 35000 | D5: =C5-B5 -> 0 | E5: =IF(B5=0,0,D5/B5) -> 0 | F5: Quote Nov 2025 for Apr 2026: re-quote needed
A6: Extra coach share (only above seat capacity) | B6: =IF(Inputs!$E$6>Inputs!$E$14,(ROUNDUP(Inputs!$E$6/Inputs!$E$14,0)-1)*Inputs!$E$16*Inputs!$E$15/Inputs!$E$5/Inputs!$E$6,0) -> 0 | C6: =IF(Inputs!$E$6>Inputs!$E$14,(ROUNDUP(Inputs!$E$6/Inputs!$E$14,0)-1)*Inputs!$E$16*Inputs!$E$15/Inputs!$E$4/Inputs!$E$6,0) -> 0 | D6: =C6-B6 -> 0 | E6: =IF(B6=0,0,D6/B6) -> 0 | F6: NOT VERIFIED coach rate
A7: e-VOA visa fee | B7: =Inputs!$E$20/Inputs!$E$5 -> 2702.7027 | C7: =Inputs!$E$19/Inputs!$E$4 -> 3934.0217 | D7: =C7-B7 -> 1231.319 | E7: =IF(B7=0,0,D7/B7) -> 0.45558804 | F7: Fee rise announced, effective date NOT VERIFIED
A8: Bali tourist levy | B8: =Inputs!$E$21/Inputs!$E$5 -> 810.81081 | C8: =Inputs!$E$21/Inputs!$E$4 -> 786.80435 | D8: =C8-B8 -> -24.006464 | E8: =IF(B8=0,0,D8/B8) -> -0.029607972 | F8: Official portal
A9: Yatri kit | B9: =Inputs!$E$22 -> 0 | C9: =Inputs!$E$22 -> 0 | D9: =C9-B9 -> 0 | E9: =IF(B9=0,0,D9/B9) -> 0 | F9: TBC
A10: Senior insurance top-up | B10: =Inputs!$E$23 -> 0 | C10: =Inputs!$E$23 -> 0 | D10: =C10-B10 -> 0 | E10: =IF(B10=0,0,D10/B10) -> 0 | F10: TBC
A11: Satvik arrangements beyond package | B11: =Inputs!$E$24 -> 0 | C11: =Inputs!$E$24 -> 0 | D11: =C11-B11 -> 0 | E11: =IF(B11=0,0,D11/B11) -> 0 | F11: TBC
A12: Hyderabad local transfers | B12: =Inputs!$E$25 -> 0 | C12: =Inputs!$E$25 -> 0 | D12: =C12-B12 -> 0 | E12: =IF(B12=0,0,D12/B12) -> 0 | F12: TBC
A13: Tour manager and accompanying devotees (cost shared by paying yatris) | B13: =(Inputs!$E$7+Inputs!$E$8)*(Inputs!$E$17+Inputs!$E$18+Inputs!$E$20/Inputs!$E$5+Inputs!$E$21/Inputs!$E$5)/Inputs!$E$6 -> 7415.444 | C13: =(Inputs!$E$7+Inputs!$E$8)*(Inputs!$E$17+Inputs!$E$18+Inputs!$E$19/Inputs!$E$4+Inputs!$E$21/Inputs!$E$4)/Inputs!$E$6 -> 7518.9279 | D13: =C13-B13 -> 103.48393 | E13: =IF(B13=0,0,D13/B13) -> 0.013955191 | F13: Assumption: 1 + 2 persons
A14: Sub-total | B14: =SUM(B4:B13) -> 93928.958 | C14: =SUM(C4:C13) -> 95239.754 | D14: =C14-B14 -> 1310.7965 | E14: =IF(B14=0,0,D14/B14) -> 0.013955191
A15: Contingency | B15: =B14*Inputs!$E$12 -> 2817.8687 | C15: =C14*Inputs!$E$12 -> 2857.1926 | D15: =C15-B15 -> 39.323895 | E15: =IF(B15=0,0,D15/B15) -> 0.013955191
A16: COST PER YATRI | B16: =B14+B15 -> 96746.826 | C16: =C14+C15 -> 98096.947 | D16: =C16-B16 -> 1350.1204 | E16: =IF(B16=0,0,D16/B16) -> 0.013955191
A17: Price before GST for the target margin (bank charges included) | B17: =B16/(1-Inputs!$E$9-Inputs!$E$13) -> 109318.45 | C17: =C16/(1-Inputs!$E$9-Inputs!$E$13) -> 110844.01 | D17: =C17-B17 -> 1525.5598 | E17: =IF(B17=0,0,D17/B17) -> 0.013955191
A18: GST | B18: =B17*Inputs!$E$10 -> 5465.9224 | C18: =C17*Inputs!$E$10 -> 5542.2004 | D18: =C18-B18 -> 76.277989 | E18: =IF(B18=0,0,D18/B18) -> 0.013955191
A19: Price including GST | B19: =B17*(1+Inputs!$E$10) -> 114784.37 | C19: =C17*(1+Inputs!$E$10) -> 116386.21 | D19: =C19-B19 -> 1601.8378 | E19: =IF(B19=0,0,D19/B19) -> 0.013955191
A20: TCS (collected from the yatri, adjustable against their income tax) | B20: =B19*Inputs!$E$11 -> 2295.6874 | C20: =C19*Inputs!$E$11 -> 2327.7242 | D20: =C20-B20 -> 32.036755 | E20: =IF(B20=0,0,D20/B20) -> 0.013955191
A21: TOTAL PAYABLE BY YATRI | B21: =B19*(1+Inputs!$E$11) -> 117080.06 | C21: =C19*(1+Inputs!$E$11) -> 118713.93 | D21: =C21-B21 -> 1633.8745 | E21: =IF(B21=0,0,D21/B21) -> 0.013955191
A23: Margin at your proposed selling price (Inputs: selling price before GST) | C23: =IF(Inputs!$E$26="","enter a price in Inputs",(Inputs!$E$26*(1-Inputs!$E$13)-C16)/Inputs!$E$26) -> enter a price in Inputs
A24: Gap: price needed minus proposed selling price | C24: =IF(Inputs!$E$26="","",C17-Inputs!$E$26)

Sheet Sensitivity
A1: Cost per yatri and price needed, by group size (current basis)
A3: Yatris | B3: Extra coaches | C3: Flights | D3: Land package | E3: Extra coach share | F3: e-VOA | G3: Levy | H3: Other (kit, insurance, Satvik, transfers) | I3: Team share (TM + devotees) | J3: Contingency | K3: COST per yatri | L3: Price before GST at target margin | M3: Incl. 5% GST | N3: Incl. TCS (total payable) | O3: Price at 5% margin | P3: Price at 10% margin | Q3: Price at 15% margin | R3: Price at 20% margin
A4: 30 | B4: =ROUNDUP(A4/Inputs!$E$14,0)-1 -> 0 | C4: =Inputs!$E$17 -> 48000 | D4: =Inputs!$E$18 -> 35000 | E4: =B4*Inputs!$E$16*Inputs!$E$15/Inputs!$E$4/A4 -> 0 | F4: =Inputs!$E$19/Inputs!$E$4 -> 3934.0217 | G4: =Inputs!$E$21/Inputs!$E$4 -> 786.80435 | H4: =Inputs!$E$22+Inputs!$E$23+Inputs!$E$24+Inputs!$E$25 -> 0 | I4: =(Inputs!$E$7+Inputs!$E$8)*(C4+D4+F4+G4)/A4 -> 8772.0826 | J4: =SUM(C4:I4)*Inputs!$E$12 -> 2894.7873 | K4: =SUM(C4:J4) -> 99387.696 | L4: =K4/(1-Inputs!$E$9-Inputs!$E$13) -> 112302.48 | M4: =L4*(1+Inputs!$E$10) -> 117917.61 | N4: =M4*(1+Inputs!$E$11) -> 120275.96 | O4: =K4/(1-0.05-Inputs!$E$13) -> 106297 | P4: =K4/(1-0.1-Inputs!$E$13) -> 112302.48 | Q4: =K4/(1-0.15-Inputs!$E$13) -> 119027.18 | R4: =K4/(1-0.2-Inputs!$E$13) -> 126608.53
A5: 35 | B5: =ROUNDUP(A5/Inputs!$E$14,0)-1 -> 0 | C5: =Inputs!$E$17 -> 48000 | D5: =Inputs!$E$18 -> 35000 | E5: =B5*Inputs!$E$16*Inputs!$E$15/Inputs!$E$4/A5 -> 0 | F5: =Inputs!$E$19/Inputs!$E$4 -> 3934.0217 | G5: =Inputs!$E$21/Inputs!$E$4 -> 786.80435 | H5: =Inputs!$E$22+Inputs!$E$23+Inputs!$E$24+Inputs!$E$25 -> 0 | I5: =(Inputs!$E$7+Inputs!$E$8)*(C5+D5+F5+G5)/A5 -> 7518.9279 | J5: =SUM(C5:I5)*Inputs!$E$12 -> 2857.1926 | K5: =SUM(C5:J5) -> 98096.947 | L5: =K5/(1-Inputs!$E$9-Inputs!$E$13) -> 110844.01 | M5: =L5*(1+Inputs!$E$10) -> 116386.21 | N5: =M5*(1+Inputs!$E$11) -> 118713.93 | O5: =K5/(1-0.05-Inputs!$E$13) -> 104916.52 | P5: =K5/(1-0.1-Inputs!$E$13) -> 110844.01 | Q5: =K5/(1-0.15-Inputs!$E$13) -> 117481.37 | R5: =K5/(1-0.2-Inputs!$E$13) -> 124964.26
A6: 40 | B6: =ROUNDUP(A6/Inputs!$E$14,0)-1 -> 1 | C6: =Inputs!$E$17 -> 48000 | D6: =Inputs!$E$18 -> 35000 | E6: =B6*Inputs!$E$16*Inputs!$E$15/Inputs!$E$4/A6 -> 996.61884 | F6: =Inputs!$E$19/Inputs!$E$4 -> 3934.0217 | G6: =Inputs!$E$21/Inputs!$E$4 -> 786.80435 | H6: =Inputs!$E$22+Inputs!$E$23+Inputs!$E$24+Inputs!$E$25 -> 0 | I6: =(Inputs!$E$7+Inputs!$E$8)*(C6+D6+F6+G6)/A6 -> 6579.062 | J6: =SUM(C6:I6)*Inputs!$E$12 -> 2858.8952 | K6: =SUM(C6:J6) -> 98155.402 | L6: =K6/(1-Inputs!$E$9-Inputs!$E$13) -> 110910.06 | M6: =L6*(1+Inputs!$E$10) -> 116455.56 | N6: =M6*(1+Inputs!$E$11) -> 118784.67 | O6: =K6/(1-0.05-Inputs!$E$13) -> 104979.04 | P6: =K6/(1-0.1-Inputs!$E$13) -> 110910.06 | Q6: =K6/(1-0.15-Inputs!$E$13) -> 117551.38 | R6: =K6/(1-0.2-Inputs!$E$13) -> 125038.73
A7: 45 | B7: =ROUNDUP(A7/Inputs!$E$14,0)-1 -> 1 | C7: =Inputs!$E$17 -> 48000 | D7: =Inputs!$E$18 -> 35000 | E7: =B7*Inputs!$E$16*Inputs!$E$15/Inputs!$E$4/A7 -> 885.88341 | F7: =Inputs!$E$19/Inputs!$E$4 -> 3934.0217 | G7: =Inputs!$E$21/Inputs!$E$4 -> 786.80435 | H7: =Inputs!$E$22+Inputs!$E$23+Inputs!$E$24+Inputs!$E$25 -> 0 | I7: =(Inputs!$E$7+Inputs!$E$8)*(C7+D7+F7+G7)/A7 -> 5848.0551 | J7: =SUM(C7:I7)*Inputs!$E$12 -> 2833.6429 | K7: =SUM(C7:J7) -> 97288.408 | L7: =K7/(1-Inputs!$E$9-Inputs!$E$13) -> 109930.4 | M7: =L7*(1+Inputs!$E$10) -> 115426.92 | N7: =M7*(1+Inputs!$E$11) -> 117735.46 | O7: =K7/(1-0.05-Inputs!$E$13) -> 104051.77 | P7: =K7/(1-0.1-Inputs!$E$13) -> 109930.4 | Q7: =K7/(1-0.15-Inputs!$E$13) -> 116513.06 | R7: =K7/(1-0.2-Inputs!$E$13) -> 123934.28
A8: 49 | B8: =ROUNDUP(A8/Inputs!$E$14,0)-1 -> 1 | C8: =Inputs!$E$17 -> 48000 | D8: =Inputs!$E$18 -> 35000 | E8: =B8*Inputs!$E$16*Inputs!$E$15/Inputs!$E$4/A8 -> 813.5664 | F8: =Inputs!$E$19/Inputs!$E$4 -> 3934.0217 | G8: =Inputs!$E$21/Inputs!$E$4 -> 786.80435 | H8: =Inputs!$E$22+Inputs!$E$23+Inputs!$E$24+Inputs!$E$25 -> 0 | I8: =(Inputs!$E$7+Inputs!$E$8)*(C8+D8+F8+G8)/A8 -> 5370.6628 | J8: =SUM(C8:I8)*Inputs!$E$12 -> 2817.1517 | K8: =SUM(C8:J8) -> 96722.207 | L8: =K8/(1-Inputs!$E$9-Inputs!$E$13) -> 109290.63 | M8: =L8*(1+Inputs!$E$10) -> 114755.16 | N8: =M8*(1+Inputs!$E$11) -> 117050.26 | O8: =K8/(1-0.05-Inputs!$E$13) -> 103446.21 | P8: =K8/(1-0.1-Inputs!$E$13) -> 109290.63 | Q8: =K8/(1-0.15-Inputs!$E$13) -> 115834.98 | R8: =K8/(1-0.2-Inputs!$E$13) -> 123213
A11: Note: the operator land slab is flat for 30 or more guests, so the cost per yatri changes with group size only through the extra coach, the shared team cost and rounding.

Sheet Open points
A1: # | B1: Open point to verify | C1: Owner
A2: 1 | B2: Flights HYD-DPS-HYD for Jun 2027: get written group quotes (MH, AirAsia/Batik). Monday 21 Jun arrival needs a Sunday-night departure, which the current AirAsia pattern does not operate. | C2: TBC
A3: 2 | B3: Return DPS to HYD times and airline: not found. | C3: TBC
A4: 3 | B4: e-VOA fee: IDR 500,000 (official page) or IDR 750,000 (announced rise, 12 Aug 2026)? Effective date. | C4: TBC
A5: 4 | B5: Hotel names, star ratings, Jun 2027 twin rate and ++ taxes (10%/11% tax, 10% service). | C5: TBC
A6: 5 | B6: Land package re-quote for Jun 2027 (4 nights), with written Satvik confirmation and whether entry tickets are included. | C6: TBC
A7: 6 | B7: ISKCON Bali Bitera: current address, programme times, group prasadam, contact. | C7: TBC
A8: 7 | B8: Restaurants: group capacity, price and no onion-garlic for Vrindavan, Madhubann, Vinayak, Shiv Sagar; boxed lunch for Bedugul. | C8: TBC
A9: 8 | B9: Entry ticket prices from official sources; senior or group concessions. | C9: TBC
A10: 9 | B10: Bali Arts Festival 2027 dates (likely overlap, Denpasar road closures). | C10: TBC
A11: 10 | B11: Menstruation rule at temples: brief women yatris; confirm site policies. | C11: TBC
A12: 11 | B12: Senior insurance (60+) group quote; medical fitness forms. | C12: TBC
A13: 12 | B13: TCS 2% and GST 5% treatment: CA confirmation. | C13: TBC
... A16: 15 | B16: Yatra team: number of tour managers and accompanying devotees. | C16: TBC
